{
 "chain_iptm": [
  0.47,
  0.34,
  0.26,
  0.21,
  0.3,
  0.12,
  0.14,
  0.21,
  0.12,
  0.11
 ],
 "chain_pair_iptm": [
  [
   0.79,
   0.65,
   0.51,
   0.4,
   0.59,
   0.24,
   0.28,
   0.41,
   0.24,
   0.93
  ],
  [
   0.65,
   null,
   null,
   null,
   null,
   null,
   null,
   null,
   null,
   0.02
  ],
  [
   0.51,
   null,
   null,
   null,
   null,
   null,
   null,
   null,
   null,
   0.02
  ],
  [
   0.4,
   null,
   null,
   null,
   null,
   null,
   null,
   null,
   null,
   0.01
  ],
  [
   0.59,
   null,
   null,
   null,
   null,
   null,
   null,
   null,
   null,
   0.01
  ],
  [
   0.24,
   null,
   null,
   null,
   null,
   null,
   null,
   null,
   null,
   0.0
  ],
  [
   0.28,
   null,
   null,
   null,
   null,
   null,
   null,
   null,
   null,
   0.0
  ],
  [
   0.41,
   null,
   null,
   null,
   null,
   null,
   null,
   null,
   null,
   0.01
  ],
  [
   0.24,
   null,
   null,
   null,
   null,
   null,
   null,
   null,
   null,
   0.01
  ],
  [
   0.93,
   0.02,
   0.02,
   0.01,
   0.01,
   0.0,
   0.0,
   0.01,
   0.01,
   0.04
  ]
 ],
 "chain_pair_pae_min": [
  [
   0.76,
   3.68,
   5.45,
   8.09,
   4.85,
   12.66,
   16.12,
   8.26,
   15.42,
   0.84
  ],
  [
   null,
   null,
   null,
   null,
   null,
   null,
   null,
   null,
   null,
   null
  ],
  [
   null,
   null,
   null,
   null,
   null,
   null,
   null,
   null,
   null,
   null
  ],
  [
   null,
   null,
   null,
   null,
   null,
   null,
   null,
   null,
   null,
   null
  ],
  [
   null,
   null,
   null,
   null,
   null,
   null,
   null,
   null,
   null,
   null
  ],
  [
   null,
   null,
   null,
   null,
   null,
   null,
   null,
   null,
   null,
   null
  ],
  [
   null,
   null,
   null,
   null,
   null,
   null,
   null,
   null,
   null,
   null
  ],
  [
   null,
   null,
   null,
   null,
   null,
   null,
   null,
   null,
   null,
   null
  ],
  [
   null,
   null,
   null,
   null,
   null,
   null,
   null,
   null,
   null,
   null
  ],
  [
   0.93,
   4.07,
   5.7,
   8.23,
   7.28,
   13.68,
   17.3,
   8.83,
   15.67,
   0.76
  ]
 ],
 "chain_ptm": [
  0.79,
  null,
  null,
  null,
  null,
  null,
  null,
  null,
  null,
  0.04
 ],
 "fraction_disordered": 0.0,
 "has_clash": 0.0,
 "iptm": 0.78,
 "ptm": 0.81,
 "ranking_score": 0.78
}