{
 "chain_iptm": [
  0.87,
  0.81,
  0.58,
  0.43,
  0.26,
  0.26,
  0.39
 ],
 "chain_pair_iptm": [
  [
   0.94,
   0.92,
   0.98,
   0.98,
   0.69,
   0.7,
   0.95
  ],
  [
   0.92,
   0.88,
   0.88,
   0.93,
   0.6,
   0.61,
   0.93
  ],
  [
   0.98,
   0.88,
   0.71,
   0.65,
   0.25,
   0.24,
   0.45
  ],
  [
   0.98,
   0.93,
   0.65,
   null,
   0.0,
   0.0,
   0.0
  ],
  [
   0.69,
   0.6,
   0.25,
   0.0,
   0.04,
   0.0,
   0.02
  ],
  [
   0.7,
   0.61,
   0.24,
   0.0,
   0.0,
   0.04,
   0.01
  ],
  [
   0.95,
   0.93,
   0.45,
   0.0,
   0.02,
   0.01,
   0.04
  ]
 ],
 "chain_pair_pae_min": [
  [
   0.76,
   1.02,
   0.81,
   0.86,
   7.3,
   6.63,
   1.15
  ],
  [
   0.98,
   0.76,
   1.87,
   1.82,
   7.97,
   8.12,
   1.25
  ],
  [
   0.85,
   2.18,
   0.76,
   1.27,
   8.69,
   8.98,
   2.43
  ],
  [
   null,
   null,
   null,
   null,
   null,
   null,
   null
  ],
  [
   7.59,
   12.64,
   18.64,
   17.89,
   0.78,
   21.33,
   12.19
  ],
  [
   7.57,
   15.97,
   17.58,
   17.72,
   20.51,
   0.76,
   18.83
  ],
  [
   2.98,
   2.48,
   8.38,
   7.57,
   12.1,
   16.73,
   0.77
  ]
 ],
 "chain_ptm": [
  0.94,
  0.88,
  0.71,
  null,
  0.04,
  0.04,
  0.04
 ],
 "fraction_disordered": 0.0,
 "has_clash": 0.0,
 "iptm": 0.91,
 "ptm": 0.92,
 "ranking_score": 0.92
}