{
 "chain_iptm": [
  0.59,
  0.59,
  0.26,
  0.25,
  0.19,
  0.14
 ],
 "chain_pair_iptm": [
  [
   0.84,
   0.87,
   0.61,
   0.66,
   0.46,
   0.32
  ],
  [
   0.87,
   0.84,
   0.67,
   0.6,
   0.46,
   0.35
  ],
  [
   0.61,
   0.67,
   0.03,
   0.0,
   0.0,
   0.0
  ],
  [
   0.66,
   0.6,
   0.0,
   0.03,
   0.0,
   0.0
  ],
  [
   0.46,
   0.46,
   0.0,
   0.0,
   0.03,
   0.01
  ],
  [
   0.32,
   0.35,
   0.0,
   0.0,
   0.01,
   0.04
  ]
 ],
 "chain_pair_pae_min": [
  [
   0.76,
   0.94,
   1.81,
   1.79,
   3.88,
   6.62
  ],
  [
   0.95,
   0.76,
   1.48,
   2.11,
   3.7,
   6.08
  ],
  [
   4.64,
   3.35,
   0.77,
   5.57,
   7.69,
   14.08
  ],
  [
   4.35,
   5.52,
   5.66,
   0.77,
   8.04,
   14.57
  ],
  [
   9.2,
   7.66,
   7.0,
   7.51,
   0.77,
   6.01
  ],
  [
   12.1,
   10.81,
   12.2,
   11.79,
   6.94,
   0.77
  ]
 ],
 "chain_ptm": [
  0.84,
  0.84,
  0.03,
  0.03,
  0.03,
  0.04
 ],
 "fraction_disordered": 0.0,
 "has_clash": 0.0,
 "iptm": 0.81,
 "ptm": 0.85,
 "ranking_score": 0.82
}